README.md
pyproject.toml
coze_workload_identity/__init__.py
coze_workload_identity/client.py
coze_workload_identity/env_keys.py
coze_workload_identity/exceptions.py
coze_workload_identity/models.py
coze_workload_identity/proxy.py
coze_workload_identity/requests.py
coze_workload_identity.egg-info/PKG-INFO
coze_workload_identity.egg-info/SOURCES.txt
coze_workload_identity.egg-info/dependency_links.txt
coze_workload_identity.egg-info/requires.txt
coze_workload_identity.egg-info/top_level.txt
tests/test_client.py
tests/test_exceptions.py
tests/test_integration_credential.py
tests/test_integration_credential_env_keys.py
tests/test_lane_support.py
tests/test_lane_support_env_keys.py
tests/test_project_env_vars.py