Metadata-Version: 2.4
Name: coze-workload-identity
Version: 0.1.5
Summary: Python SDK for Coze workload identity authentication
Author-email: SDK Team <sdk@example.com>
License: MIT
Requires-Python: >=3.8
Requires-Dist: requests>=2.25.0
Requires-Dist: urllib3>=1.26.0
Provides-Extra: dev
Requires-Dist: pytest>=6.0.0; extra == "dev"
Requires-Dist: pytest-cov>=2.10.0; extra == "dev"
Requires-Dist: black>=21.0.0; extra == "dev"
Requires-Dist: flake8>=3.8.0; extra == "dev"
Requires-Dist: mypy>=0.800; extra == "dev"
